odoo/addons/fieldservice_activity/README.rst
odoo/addons/fieldservice_activity/__init__.py
odoo/addons/fieldservice_activity/__manifest__.py
odoo/addons/fieldservice_activity/i18n/es_AR.po
odoo/addons/fieldservice_activity/i18n/es_CL.po
odoo/addons/fieldservice_activity/i18n/fieldservice_activity.pot
odoo/addons/fieldservice_activity/i18n/pt_BR.po
odoo/addons/fieldservice_activity/i18n/pt_PT.po
odoo/addons/fieldservice_activity/models/__init__.py
odoo/addons/fieldservice_activity/models/fsm_activity.py
odoo/addons/fieldservice_activity/models/fsm_order.py
odoo/addons/fieldservice_activity/models/fsm_template.py
odoo/addons/fieldservice_activity/readme/CONFIGURE.rst
odoo/addons/fieldservice_activity/readme/CONTRIBUTORS.rst
odoo/addons/fieldservice_activity/readme/CREDITS.rst
odoo/addons/fieldservice_activity/readme/DESCRIPTION.rst
odoo/addons/fieldservice_activity/readme/USAGE.rst
odoo/addons/fieldservice_activity/security/ir.model.access.csv
odoo/addons/fieldservice_activity/static/description/icon.png
odoo/addons/fieldservice_activity/static/description/index.html
odoo/addons/fieldservice_activity/tests/__init__.py
odoo/addons/fieldservice_activity/tests/test_fsm_activity.py
odoo/addons/fieldservice_activity/views/fsm_order.xml
odoo/addons/fieldservice_activity/views/fsm_template.xml
odoo13_addon_fieldservice_activity-13.0.1.0.1.dist-info/METADATA
odoo13_addon_fieldservice_activity-13.0.1.0.1.dist-info/WHEEL
odoo13_addon_fieldservice_activity-13.0.1.0.1.dist-info/top_level.txt
odoo13_addon_fieldservice_activity-13.0.1.0.1.dist-info/RECORD
