Metadata-Version: 2.1
Name: odoo13-addon-fieldservice-activity
Version: 13.0.1.0.1
Summary: Field Service Activities are a set of actions that need to be performed on a service order
Home-page: https://github.com/OCA/field-service
Author: Open Source Integrators, Odoo Community Association (OCA)
Author-email: support@odoo-community.org
License: AGPL-3
Platform: UNKNOWN
Classifier: Programming Language :: Python
Classifier: Framework :: Odoo
Classifier: License :: OSI Approved :: GNU Affero General Public License v3
Classifier: Development Status :: 4 - Beta
Requires-Python: >=3.5
Requires-Dist: odoo13-addon-fieldservice
Requires-Dist: odoo (<13.1dev,>=13.0a)
